search/__init__.py
search/find.py
SearchInFile-1.0.0.dist-info/LICENSE
SearchInFile-1.0.0.dist-info/METADATA
SearchInFile-1.0.0.dist-info/WHEEL
SearchInFile-1.0.0.dist-info/top_level.txt
SearchInFile-1.0.0.dist-info/RECORD
